water_column_sonar_processing/__init__.py
water_column_sonar_processing/aws/__init__.py
water_column_sonar_processing/aws/dynamodb_manager.py
water_column_sonar_processing/aws/s3_manager.py
water_column_sonar_processing/aws/s3fs_manager.py
water_column_sonar_processing/aws/sns_manager.py
water_column_sonar_processing/aws/sqs_manager.py
water_column_sonar_processing/cruise/__init__.py
water_column_sonar_processing/cruise/create_empty_zarr_store.py
water_column_sonar_processing/cruise/datatree_manager.py
water_column_sonar_processing/cruise/resample_regrid.py
water_column_sonar_processing/geometry/__init__.py
water_column_sonar_processing/geometry/elevation_manager.py
water_column_sonar_processing/geometry/geometry_manager.py
water_column_sonar_processing/geometry/line_simplification.py
water_column_sonar_processing/geometry/pmtile_generation.py
water_column_sonar_processing/geometry/spatiotemporal.py
water_column_sonar_processing/index/__init__.py
water_column_sonar_processing/index/index_manager.py
water_column_sonar_processing/model/__init__.py
water_column_sonar_processing/model/zarr_manager.py
water_column_sonar_processing/processing/__init__.py
water_column_sonar_processing/processing/raw_to_netcdf.py
water_column_sonar_processing/processing/raw_to_zarr.py
water_column_sonar_processing/utility/__init__.py
water_column_sonar_processing/utility/cleaner.py
water_column_sonar_processing/utility/constants.py
water_column_sonar_processing/utility/pipeline_status.py
water_column_sonar_processing/utility/timestamp.py
water_column_sonar_processing-26.1.17.dist-info/licenses/LICENSE
water_column_sonar_processing-26.1.17.dist-info/METADATA
water_column_sonar_processing-26.1.17.dist-info/WHEEL
water_column_sonar_processing-26.1.17.dist-info/top_level.txt
water_column_sonar_processing-26.1.17.dist-info/RECORD
