Metadata-Version: 2.4
Name: water-column-sonar-processing
Version: 26.1.17
Summary: Processing tool for water column sonar data.
Author-email: Rudy Klucik <rudy.klucik@noaa.gov>
Maintainer-email: Rudy Klucik <rudy.klucik@noaa.gov>
License-Expression: MIT
Project-URL: Homepage, https://echo.fish
Project-URL: Repository, https://github.com/CI-CMG/water-column-sonar-processing
Project-URL: Issues, https://github.com/CI-CMG/water-column-sonar-processing/issues
Keywords: ocean,sonar,water column,zarr
Requires-Python: >=3.12
License-File: LICENSE
Requires-Dist: boto3==1.41.5
Requires-Dist: boto3-stubs
Requires-Dist: botocore==1.41.5
Requires-Dist: build
Requires-Dist: echopype==0.11.0
Requires-Dist: fiona==1.10.1
Requires-Dist: geopandas==1.1.2
Requires-Dist: importlib==1.0.4
Requires-Dist: mock
Requires-Dist: moto[all]==5.1.20
Requires-Dist: moto[server]==5.1.20
Requires-Dist: multidict==6.7.0
Requires-Dist: netcdf4==1.7.3
Requires-Dist: numpy==2.4.1
Requires-Dist: pandas==3.0.0
Requires-Dist: pandas-stubs
Requires-Dist: pooch==1.8.2
Requires-Dist: pyarrow==23.0.0
Requires-Dist: pykalman==0.11.1
Requires-Dist: python-dotenv
Requires-Dist: requests==2.32.5
Requires-Dist: ruff==0.14.14
Requires-Dist: s3fs==2026.1.0
Requires-Dist: scipy==1.17.0
Requires-Dist: setuptools==80.10.1
Requires-Dist: shapely==2.1.2
Requires-Dist: xarray==2025.12.0
Requires-Dist: zarr==3.1.5
Dynamic: license-file
